sparrow_rtdetr/__init__.py
sparrow_rtdetr/box_ops.py
sparrow_rtdetr/common.py
sparrow_rtdetr/config.py
sparrow_rtdetr/post_processor.py
sparrow_rtdetr/rtdetr.py
sparrow_rtdetr/rtdetr_test.py
sparrow_rtdetr/utils.py
sparrow_rtdetr/backbone/__init__.py
sparrow_rtdetr/backbone/backbone_common.py
sparrow_rtdetr/backbone/presnet.py
sparrow_rtdetr/decoder/__init__.py
sparrow_rtdetr/decoder/decoder_common.py
sparrow_rtdetr/decoder/denoising.py
sparrow_rtdetr/decoder/rtdetr_transformer.py
sparrow_rtdetr/decoder/utils.py
sparrow_rtdetr/encoder/__init__.py
sparrow_rtdetr/encoder/encoder_common.py
sparrow_rtdetr/encoder/hybrid_encoder.py
sparrow_rtdetr/loss/__init__.py
sparrow_rtdetr/loss/hungarian_matcher.py
sparrow_rtdetr/loss/set_criterion.py
sparrow_rtdetr-0.1.0.dist-info/LICENSE
sparrow_rtdetr-0.1.0.dist-info/METADATA
sparrow_rtdetr-0.1.0.dist-info/WHEEL
sparrow_rtdetr-0.1.0.dist-info/top_level.txt
sparrow_rtdetr-0.1.0.dist-info/RECORD
