Metadata-Version: 2.1
Name: sparrow-rtdetr
Version: 0.1.0
Author: Sparrow Computing
Author-email: ben@sparrow.dev
License-File: LICENSE
Requires-Dist: fire
Requires-Dist: scipy
Requires-Dist: torch ==2.0.1
Requires-Dist: torchvision ==0.15.2
Provides-Extra: dev
Requires-Dist: jupyter ; extra == 'dev'
Requires-Dist: pytest ; extra == 'dev'
Requires-Dist: pytest-cov ; extra == 'dev'
